stablehlo_coreml/__init__.py
stablehlo_coreml/converter.py
stablehlo_coreml/ops_register.py
stablehlo_coreml/padding.py
stablehlo_coreml/reductions.py
stablehlo_coreml/sort_utils.py
stablehlo_coreml/translation_context.py
stablehlo_coreml/utils.py
stablehlo_coreml/passes/remove_noop_slice_update.py
stablehlo_coreml/passes/utils.py
stablehlo_coreml_experimental-0.0.14.dist-info/METADATA
stablehlo_coreml_experimental-0.0.14.dist-info/WHEEL
stablehlo_coreml_experimental-0.0.14.dist-info/licenses/LICENSE
stablehlo_coreml_experimental-0.0.14.dist-info/RECORD
