Metadata-Version: 2.4
Name: stablehlo-coreml-experimental
Version: 0.0.14
Summary: Convert StableHLO models into Apple Core ML format
Project-URL: Homepage, https://github.com/kasper0406/stablehlo-coreml
Project-URL: Issues, https://github.com/kasper0406/stablehlo-coreml/issues
Author-email: Kasper Nielsen <kasper0406@gmail.com>
License-File: LICENSE
Keywords: converter,coreml,coremltools,hlo,machinelearning,ml,neural,stablehlo,xla
Classifier: Development Status :: 3 - Alpha
Classifier: Intended Audience :: Developers
Classifier: Intended Audience :: End Users/Desktop
Classifier: License :: OSI Approved :: MIT License
Classifier: Operating System :: MacOS :: MacOS X
Classifier: Programming Language :: Python
Classifier: Topic :: Scientific/Engineering
Classifier: Topic :: Software Development
Requires-Python: >=3.9
Requires-Dist: coremltools>=9.0; python_version >= '3.10' and python_version <= '3.13'
Requires-Dist: jax>=0.8.1
Requires-Dist: numpy~=2.0
